{"success": true, "message": "Fetched question.", "data": {"showTimer": true, "showAttemptInsight": true, "playSounds": true, "dontShowCorrectAnswerImmediately": false, "_id": "6151e8639827f48dfa988514", "type": "singleCorrect", "level": null, "category": null, "approximateTimeRequired": null, "imageBaseUrl": null, "helperText": null, "source": "NTAS1", "classes": [], "exams": ["615d76b2c52ffa3c944600df"], "subjects": ["615d708dbd4a37c4058ee5a8"], "chapters": ["615d6fec2b295b085ab6eb92"], "topics": [], "concepts": [], "microConcepts": [], "questionLabels": [{"title": "NTA Abhyas Paper", "value": "64", "isVisible": true}], "previousYearPapers": [], "question": {"text": "The binding energy of a satellite of mass&nbsp;<math xmlns=\"http://www.w3.org/1998/Math/MathML\"><mi>m</mi></math> in an orbit of radius&nbsp;<math xmlns=\"http://www.w3.org/1998/Math/MathML\"><mi>r</mi></math> is (<math xmlns=\"http://www.w3.org/1998/Math/MathML\"><mi>R</mi></math> = radius of the earth,&nbsp;<math xmlns=\"http://www.w3.org/1998/Math/MathML\"><mi mathvariant=\"normal\">g</mi></math> = acceleration due to gravity)", "image": null}, "options": [{"id": "87yQC", "text": "<math xmlns=\"http://www.w3.org/1998/Math/MathML\"><mfrac><mrow><mi>m</mi><mi mathvariant=\"normal\">g</mi><msup><mi>R</mi><mn>2</mn></msup></mrow><mi>r</mi></mfrac></math>", "image": null, "isCorrect": false}, {"id": "uR3aj", "text": "<math xmlns=\"http://www.w3.org/1998/Math/MathML\"><mfrac><mrow><mi>m</mi><mi mathvariant=\"normal\">g</mi><msup><mi>R</mi><mn>2</mn></msup></mrow><mrow><mn>2</mn><mi>r</mi></mrow></mfrac></math>", "image": null, "isCorrect": true}, {"id": "NVzC7", "text": "<math xmlns=\"http://www.w3.org/1998/Math/MathML\"><mfrac><mrow><mi>m</mi><mi mathvariant=\"normal\">g</mi><msup><mi>R</mi><mn>2</mn></msup></mrow><mrow><mn>4</mn><mi>r</mi></mrow></mfrac></math>", "image": null, "isCorrect": false}, {"id": "76opD", "text": "<math xmlns=\"http://www.w3.org/1998/Math/MathML\"><mfrac><mrow><mn>2</mn><mi>m</mi><mi mathvariant=\"normal\">g</mi><msup><mi>R</mi><mn>2</mn></msup></mrow><mi>r</mi></mfrac></math>", "image": null, "isCorrect": false}], "correctValue": null, "solution": {"text": "The energy required to remove the satellite from its orbit around the earth to infinity is called binding energy of the satellite. It is equal to negative of total mechanical energy of a satellite in its orbit.<br />Thus,<br />The binding energy of the Earth-satellite system,<br /><br />&nbsp;&nbsp;&nbsp;&nbsp;&nbsp;&nbsp;&nbsp;&nbsp;<math> <mrow> <mtext>E</mtext> <mo>=</mo> <mfrac> <mrow> <mo>-</mo> <mtext>GMm</mtext> </mrow> <mrow> <mn>2</mn> <mtext>r</mtext> </mrow> </mfrac> </mrow> </math><br /><br />using,&nbsp;&nbsp;<math><mrow><mtext>g</mtext> <mo>=</mo> <mfrac> <mrow> <mtext>GM</mtext> </mrow> <mrow> <msup> <mtext>R</mtext> <mn>2</mn> </msup> </mrow> </mfrac> </mrow> </math><br /><br /><math> <mrow> <mo>\u21d2&nbsp;&nbsp;&nbsp;</mo> <mtext>GM</mtext> <mo>=</mo> <msup> <mtext>gR</mtext> <mn>2</mn> </msup> </mrow> </math><br /><br /><math xmlns=\"http://www.w3.org/1998/Math/MathML\"><mo>\u2234&nbsp;&nbsp;</mo><mi>BE</mi><mo>=</mo><mfrac><mrow><mi mathvariant=\"normal\">g</mi><mi mathvariant=\"normal\">m</mi><msup><mi mathvariant=\"normal\">R</mi><mn>2</mn></msup></mrow><mrow><mn>2</mn><mi mathvariant=\"normal\">r</mi></mrow></mfrac></math>&nbsp;", "image": null}, "videoSolution": null, "numericalLowerLimit": null, "numericalUpperLimit": null, "cpyqbSubjects": ["61bb58181213731910ea0b70", "61c055eae8ce0dc8a5c62d33", "616057750283de43c87e3e1b", "61964fe0a5a5260118868021", "61964f81a5a526011886801d", "629f39e4ac11b26562e0625b", "616057920283de43c87e3e1e", "615f0c729476412f48314dab", "61a8a2c2e8ce0dc8a5c62d2d", "629105adee9e3ae00d63352b", "629f385f263330a77be9fa7d", "616056cd0283de43c87e3e15", "616057190283de43c87e3e18", "62962075e7f8e9ac4daeafd7", "64d50bd73df7f4a7f3017f6f", "66b79b34d4b564dfab4f94cc", "678ea9a09cc79e5f592bdc11", "67fa5fef4468eb1307ceb0ad", "6807d2ad647479b8e8696479"], "cpyqbChapters": ["61964c7d0464ec48eebad3e0", "61e7bd7e6b5fb113f0acb24c", "616023d0c98042c9b38a7982", "61c089b2a61e4eb3e272a598", "61964c7cb670fcf043c4b446", "616023d2145ccffd4235bb42", "616023cfe4a89d96c568e4cf", "61bb8228aa33ae8ae3f09705", "616023d351fc6e088c80fe27", "616023d1aaba018d1712f011", "62962122c5888d21e89ca99b", "629109ec59cb8652edec1bbc", "629f3a90bd521fefb89eaea5", "629f390baae215e1113a73a0", "64eb06c13118f713ecfef082", "66d58553a75f05ee8564f662", "67921d631d5b5072da5e9aa3", "67fdff47378e1624ea7b698e", "6809202b3a10446a207fdee0"], "cpyqbExams": ["615f0e999476412f48314daf", "616059af0283de43c87e3e23"]}}