{"success": true, "message": "Fetched question.", "data": {"showTimer": true, "showAttemptInsight": true, "playSounds": true, "dontShowCorrectAnswerImmediately": false, "_id": "6151e863761cc684e4323a76", "type": "singleCorrect", "level": null, "category": null, "approximateTimeRequired": null, "imageBaseUrl": null, "helperText": null, "source": "NTAS1", "classes": [], "exams": ["615d76b2c52ffa3c944600df"], "subjects": ["615d708dbd4a37c4058ee5a8"], "chapters": ["615d6fed2b295b085ab6eb95"], "topics": [], "concepts": [], "microConcepts": [], "questionLabels": [{"title": "NTA Abhyas Paper", "value": "47", "isVisible": true}], "previousYearPapers": [], "question": {"text": "As shown in diagram,&nbsp;<math xmlns=\"http://www.w3.org/1998/Math/MathML\"><mi>AB</mi></math> is a rod of length <math xmlns=\"http://www.w3.org/1998/Math/MathML\"><mn>30</mn><mo>&nbsp;</mo><mi>cm</mi></math>&nbsp;and area of cross section <math xmlns=\"http://www.w3.org/1998/Math/MathML\"><mn>1</mn><mo>.</mo><mn>0</mn><mo>&nbsp;</mo><msup><mi>cm</mi><mn>2</mn></msup></math>&nbsp;and thermal conductivity <math xmlns=\"http://www.w3.org/1998/Math/MathML\"><mn>336</mn><mo>&nbsp;</mo><mi>SI</mi><mo>&nbsp;</mo><mi>units</mi></math>. The ends <math xmlns=\"http://www.w3.org/1998/Math/MathML\"><mi mathvariant=\"normal\">A</mi></math>&nbsp;and <math xmlns=\"http://www.w3.org/1998/Math/MathML\"><mi mathvariant=\"normal\">B</mi></math>&nbsp;are maintained at temperatures <math xmlns=\"http://www.w3.org/1998/Math/MathML\"><mn>20</mn><mo>&nbsp;</mo><mo>\u00b0</mo><mi mathvariant=\"normal\">C</mi></math>and <math xmlns=\"http://www.w3.org/1998/Math/MathML\"><mn>40</mn><mo>&nbsp;</mo><mo>\u00b0</mo><mi mathvariant=\"normal\">C</mi></math>, respectively. A point <math xmlns=\"http://www.w3.org/1998/Math/MathML\"><mi mathvariant=\"normal\">C</mi></math>&nbsp;of this rod is connected to a box <math xmlns=\"http://www.w3.org/1998/Math/MathML\"><mi mathvariant=\"normal\">D</mi></math>, containing ice at <math xmlns=\"http://www.w3.org/1998/Math/MathML\"><mn>0</mn><mo>&nbsp;</mo><mo>\u00b0</mo><mi mathvariant=\"normal\">C</mi></math>, through a highly conducting wire of negligible heat capacity. The rate at which ice melts in the box is (assume latent heat of fusion for ice <math xmlns=\"http://www.w3.org/1998/Math/MathML\"><msub><mi>L</mi><mi>f</mi></msub><mo>=</mo><mn>80</mn><mo>&nbsp;</mo><mi>cal</mi><mo>&nbsp;</mo><msup><mi mathvariant=\"normal\">g</mi><mrow><mo>-</mo><mn>1</mn></mrow></msup></math>)<br />\r<br />\r<img alt=\"\" src=\"https://cdn-question-pool.getmarks.app/nta_abhyas/jee_main/images/EM0029825_Question.jpg\" style=\"width: 249px; height: 123px;\" />", "image": null}, "options": [{"id": "6UUiN", "text": "<math xmlns=\"http://www.w3.org/1998/Math/MathML\"><mn>84</mn><mo>&nbsp;</mo><mi>mg</mi><mo>&nbsp;</mo><msup><mi mathvariant=\"normal\">s</mi><mrow><mo>-</mo><mn>1</mn></mrow></msup></math>", "image": null, "isCorrect": false}, {"id": "m4CxM", "text": "<math xmlns=\"http://www.w3.org/1998/Math/MathML\"><mn>84</mn><mo>&nbsp;</mo><mi mathvariant=\"normal\">g</mi><mo>&nbsp;</mo><msup><mi mathvariant=\"normal\">s</mi><mrow><mo>-</mo><mn>1</mn></mrow></msup></math>", "image": null, "isCorrect": false}, {"id": "9tbBz", "text": "<math xmlns=\"http://www.w3.org/1998/Math/MathML\"><mn>20</mn><mo>&nbsp;</mo><mi>mg</mi><mo>&nbsp;</mo><msup><mi mathvariant=\"normal\">s</mi><mrow><mo>-</mo><mn>1</mn></mrow></msup></math>", "image": null, "isCorrect": false}, {"id": "hiWmp", "text": "<math xmlns=\"http://www.w3.org/1998/Math/MathML\"><mn>40</mn><mo>&nbsp;</mo><mi>mg</mi><mo>&nbsp;</mo><msup><mi mathvariant=\"normal\">s</mi><mrow><mo>-</mo><mn>1</mn></mrow></msup></math>", "image": null, "isCorrect": true}], "correctValue": null, "solution": {"text": "Thermal resistance of <math> <mrow> <mtext>AC</mtext> <mo>=</mo> <mfrac> <mrow> <mtext>L</mtext> </mrow> <mrow> <mtext>KA</mtext> </mrow> </mfrac> <mo>=</mo> <mfrac> <mrow> <mtext>0.1</mtext> </mrow> <mrow> <mn>3</mn> <mn>3</mn> <mn>6</mn> <mo>\u00d7</mo> <mn>1</mn> <msup> <mn>0</mn> <mrow> <mo>-</mo> <mn>4</mn> </mrow> </msup> </mrow> </mfrac> <mo>=</mo> <mfrac> <mrow> <mn>1</mn> <msup> <mn>0</mn> <mn>3</mn> </msup> </mrow> <mrow> <mn>3</mn> <mn>3</mn> <mn>6</mn> </mrow> </mfrac> <mo>=</mo> <mtext>R</mtext> <mfenced close=\")\" open=\"(\" separators=\",\"> <mrow> <mtext>let</mtext> </mrow> </mfenced> </mrow> </math><br /><br /><img alt=\"\" src=\"https://cdn-question-pool.getmarks.app/nta_abhyas/jee_main/images/EM0029825_Ans.jpg\" style=\"width: 243px; height: 130px;\" /><br /><br />Thermal resistance of <math> <mrow> <mtext>BC</mtext> <mo>=</mo> <mfrac> <mrow> <mtext>0.2</mtext> </mrow> <mrow> <mn>3</mn> <mn>3</mn> <mn>6</mn> <mo>\u00d7</mo> <mn>1</mn> <msup> <mn>0</mn> <mrow> <mo>-</mo> <mn>4</mn> </mrow> </msup> </mrow> </mfrac> <mo>=</mo> <mn>2</mn> <mtext>R</mtext> </mrow> </math><br /><br />Heat flow rates are<br /><br /><math> <mrow> <msub> <mtext>H</mtext> <mn>1</mn> </msub> <mo>=</mo> <mfrac> <mrow> <mn>2</mn> <mn>0</mn> </mrow> <mrow> <mtext>R</mtext> </mrow> </mfrac> <mtext>;&nbsp;&nbsp;</mtext> <msub> <mtext>H</mtext> <mn>2</mn> </msub> <mo>=</mo> <mfrac> <mrow> <mn>4</mn> <mn>0</mn> </mrow> <mrow> <mn>2</mn> <mtext>R</mtext> </mrow> </mfrac> <mo>=</mo> <mfrac> <mrow> <mn>2</mn> <mn>0</mn> </mrow> <mrow> <mtext>R</mtext> </mrow> </mfrac> </mrow> </math><br /><br />undefined<br /><br />&nbsp;&nbsp;&nbsp;<math> <mrow> <mo>=</mo> <mfrac> <mrow> <mn>1</mn> <mn>3</mn> <mn>4</mn> <mn>4</mn> <mn>0</mn> </mrow> <mrow> <mn>1</mn> <msup> <mn>0</mn> <mn>3</mn> </msup> </mrow> </mfrac> <mo>=</mo> <mtext>13.44 W</mtext> </mrow> </math><br /><br />Rate of melting of ice<br /><br /><math xmlns=\"http://www.w3.org/1998/Math/MathML\"><mo>=</mo><mfrac><mtext>H</mtext><msub><mtext>L</mtext><mtext>f</mtext></msub></mfrac><mo>=</mo><mfrac><mtext>13.44/4.2</mtext><mrow><mn>8</mn><mn>0</mn></mrow></mfrac><mo>&nbsp;</mo><msup><mtext>g&nbsp;s</mtext><mtext>-1</mtext></msup><mo>=</mo><mn>4</mn><mn>0</mn><mo>&nbsp;</mo><mi>mg</mi><mo>&nbsp;</mo><msup><mi mathvariant=\"normal\">s</mi><mrow><mo>-</mo><mn>1</mn></mrow></msup></math>", "image": null}, "videoSolution": null, "numericalLowerLimit": null, "numericalUpperLimit": null, "cpyqbSubjects": ["61bb58181213731910ea0b70", "61c055eae8ce0dc8a5c62d33", "616057750283de43c87e3e1b", "61964fe0a5a5260118868021", "61964f81a5a526011886801d", "629f39e4ac11b26562e0625b", "616057920283de43c87e3e1e", "615f0c729476412f48314dab", "61a8a2c2e8ce0dc8a5c62d2d", "629105adee9e3ae00d63352b", "629f385f263330a77be9fa7d", "616056cd0283de43c87e3e15", "616057190283de43c87e3e18", "62962075e7f8e9ac4daeafd7", "64d50bd73df7f4a7f3017f6f", "66b79b34d4b564dfab4f94cc", "678ea9a09cc79e5f592bdc11", "67fa5fef4468eb1307ceb0ad", "6807d2ad647479b8e8696479"], "cpyqbChapters": ["616023e599225f756e5df101", "616023e3445073e7f19122db", "61bb8229fce3576e46202d7d", "616023e0ffc8649daddda513", "61e7bd7f80092b5aa328b5a1", "616023e23a74832357599443", "616023e361589c931bc035b7", "61964c81150b027922bafad8", "61c089b4384657354ede4c09", "61964c81e74f86f9041974e2", "629f390e0537a44301966fe8", "629621250160e8ee846a120c", "629109f1da1b4d5a11b7952f", "629f3a930c61425b93824746", "64eb06bf3118f713ecfef06f", "66d58553a75f05ee8564f668", "67921d611d5b5072da5e9a8e", "67fdff4f378e1624ea7b69fd", "680920293a10446a207fdec5"], "cpyqbExams": ["615f0e999476412f48314daf", "616059af0283de43c87e3e23"]}}