{"success": true, "message": "Fetched question.", "data": {"showTimer": true, "showAttemptInsight": true, "playSounds": true, "dontShowCorrectAnswerImmediately": false, "_id": "6151e863538500a4623ce631", "type": "singleCorrect", "level": null, "category": null, "approximateTimeRequired": null, "imageBaseUrl": null, "helperText": null, "source": "NTAS1", "classes": [], "exams": ["615d76b2c52ffa3c944600df"], "subjects": ["615d708dbd4a37c4058ee5a8"], "chapters": ["615d6fed2b295b085ab6eb9f"], "topics": [], "concepts": [], "microConcepts": [], "questionLabels": [{"title": "NTA Abhyas Paper", "value": "56", "isVisible": true}], "previousYearPapers": [], "question": {"text": "A metal bar <math xmlns=\"http://www.w3.org/1998/Math/MathML\"><mi>AB</mi></math> can slide on two parallel thick metallic rails separated by a distance <math xmlns=\"http://www.w3.org/1998/Math/MathML\"><mi>l</mi></math>. A resistance <math xmlns=\"http://www.w3.org/1998/Math/MathML\"><mi>R</mi></math> and an inductance <math xmlns=\"http://www.w3.org/1998/Math/MathML\"><mi>L</mi></math> are connected to the rails as shown in the figure. A long straight wire, carrying a constant current <math xmlns=\"http://www.w3.org/1998/Math/MathML\"><msub><mi>I</mi><mn>0</mn></msub></math> is placed in the plane of the rails as shown. The bar <math xmlns=\"http://www.w3.org/1998/Math/MathML\"><mi>AB</mi></math> is held at rest at a distance <math xmlns=\"http://www.w3.org/1998/Math/MathML\"><msub><mi>x</mi><mn>0</mn></msub></math> from the long wire. At&nbsp;<math xmlns=\"http://www.w3.org/1998/Math/MathML\"><mo>&nbsp;</mo><mi>t</mi><mo>&nbsp;</mo><mo>=</mo><mo>&nbsp;</mo><mn>0</mn></math>, it is made to slide on the rails away from the wire.<br />\r<br />\r<img alt=\"\" height=\"157\" src=\"https://cdn-question-pool.getmarks.app/nta_abhyas/jee_main/images/EM0009092_Ques1_1.jpg\" width=\"185\" /><br />\r<br />\r&nbsp;It is observed that at time<math xmlns=\"http://www.w3.org/1998/Math/MathML\"><mo>&nbsp;</mo><mi>t</mi><mo>=</mo><mi>T</mi></math>, the metal bar <math xmlns=\"http://www.w3.org/1998/Math/MathML\"><mi>AB</mi></math> is at a distance of <math xmlns=\"http://www.w3.org/1998/Math/MathML\"><mn>2</mn><msub><mi>x</mi><mn>0</mn></msub></math> from the long wire and the resistance <math xmlns=\"http://www.w3.org/1998/Math/MathML\"><mi>R</mi></math> carries a current <math xmlns=\"http://www.w3.org/1998/Math/MathML\"><msub><mi>i</mi><mn>1</mn></msub></math>. The net charge that has flown through resistance <math xmlns=\"http://www.w3.org/1998/Math/MathML\"><mi>R</mi></math> from <math xmlns=\"http://www.w3.org/1998/Math/MathML\"><mi>t</mi><mo>=</mo><mn>0</mn></math> to <math xmlns=\"http://www.w3.org/1998/Math/MathML\"><mi>t</mi><mo>=</mo><mi>T</mi></math> is", "image": null}, "options": [{"id": "SZ2ot", "text": "<math xmlns=\"http://www.w3.org/1998/Math/MathML\"><mfrac><mn>1</mn><mi>R</mi></mfrac><mfenced open=\"[\" close=\"]\"><mrow><mfrac><mrow><msub><mi>&#x3BC;</mi><mn>0</mn></msub><mi>l</mi></mrow><mrow><mn>2</mn><mi>&#x3C0;</mi></mrow></mfrac><mtext>ln</mtext><mfenced><mn>2</mn></mfenced><mo>-</mo><mi>L</mi><msub><mi>i</mi><mn>1</mn></msub></mrow></mfenced></math>", "image": null, "isCorrect": false}, {"id": "w09y9", "text": "<math xmlns=\"http://www.w3.org/1998/Math/MathML\"><mfrac><mn>1</mn><mi>R</mi></mfrac><mfenced open=\"[\" close=\"]\"><mrow><mfrac><mrow><msub><mi>&#x3BC;</mi><mn>0</mn></msub><msub><mi>I</mi><mn>0</mn></msub><mi>l</mi></mrow><mi>&#x3C0;</mi></mfrac><mtext>ln</mtext><mfenced><mn>2</mn></mfenced><mo>-</mo><mi>L</mi><msub><mi>i</mi><mn>1</mn></msub></mrow></mfenced></math>", "image": null, "isCorrect": false}, {"id": "qNh1H", "text": "<math xmlns=\"http://www.w3.org/1998/Math/MathML\"><mfrac><mn>1</mn><mi>R</mi></mfrac><mfenced close=\"]\" open=\"[\"><mrow><mfrac><mrow><msub><mi>\u03bc</mi><mn>0</mn></msub><msub><mi>I</mi><mn>0</mn></msub><mi>l</mi></mrow><mrow><mn>2</mn><mi>\u03c0</mi></mrow></mfrac><mtext>ln</mtext><mfenced><mn>2</mn></mfenced><mo>-</mo><mi>L</mi><msub><mi>i</mi><mn>1</mn></msub></mrow></mfenced></math>", "image": null, "isCorrect": true}, {"id": "MFViG", "text": "<math xmlns=\"http://www.w3.org/1998/Math/MathML\"><mfrac><mn>1</mn><mi>R</mi></mfrac><mfenced open=\"[\" close=\"]\"><mrow><mfrac><mrow><msub><mi>&#x3BC;</mi><mn>0</mn></msub><msub><mi>I</mi><mn>0</mn></msub></mrow><mrow><mn>2</mn><mi>&#x3C0;</mi></mrow></mfrac><mtext>ln</mtext><mfenced><mn>2</mn></mfenced><mo>-</mo><mi>L</mi><msub><mi>i</mi><mn>1</mn></msub></mrow></mfenced></math>", "image": null, "isCorrect": false}], "correctValue": null, "solution": {"text": "Let v be velocity of AB when AB is at a distance x from the wire,<br /><br /><math> <mrow> <msub> <mtext mathvariant=\"italic\">e</mtext> <mtext mathvariant=\"italic\">AB</mtext> </msub> <mo>=</mo> <mtext mathvariant=\"italic\">B</mtext> <mtext mathvariant=\"italic\">.</mtext> <mi>\u2113</mi> <mtext mathvariant=\"italic\">.</mtext> <mtext mathvariant=\"italic\">v</mtext> <mo>=</mo> <mfrac> <mrow> <msub> <mi>\u03bc</mi> <mn>0</mn> </msub> <msub> <mtext mathvariant=\"italic\">I</mtext> <mn>0</mn> </msub> </mrow> <mrow> <mn>2</mn> <mi>\u03c0</mi> <mi>x</mi> </mrow> </mfrac> <mtext mathvariant=\"italic\">I</mtext> <mtext mathvariant=\"italic\">.</mtext> <mtext mathvariant=\"italic\">v</mtext> <mo>=</mo> <mfrac> <mrow> <mtext mathvariant=\"italic\">d</mtext> <mi>\u03d5</mi> </mrow> <mrow> <mtext mathvariant=\"italic\">d</mtext> <mtext mathvariant=\"italic\">t</mtext> </mrow> </mfrac> </mrow> </math><br /><br />For circuit Loop,<br /><br /><math> <mrow> <mfrac> <mrow> <mtext mathvariant=\"italic\">d</mtext> <mi>\u03d5</mi> </mrow> <mrow> <mtext mathvariant=\"italic\">d</mtext> <mtext mathvariant=\"italic\">t</mtext> </mrow> </mfrac> <mo>-</mo> <mtext mathvariant=\"italic\">i</mtext> <mtext mathvariant=\"italic\">R</mtext> <mo>-</mo> <mtext mathvariant=\"italic\">L</mtext> <mfrac> <mrow> <mtext mathvariant=\"italic\">d</mtext> <mtext mathvariant=\"italic\">i</mtext> </mrow> <mrow> <mtext mathvariant=\"italic\">d</mtext> <mtext mathvariant=\"italic\">t</mtext> </mrow> </mfrac> <mo>=</mo> <mn>0</mn> </mrow> </math><br /><br /><math> <mrow> <mfrac> <mrow> <mtext mathvariant=\"italic\">d</mtext> <mi>\u03d5</mi> </mrow> <mrow> <mtext mathvariant=\"italic\">d</mtext> <mtext mathvariant=\"italic\">t</mtext> </mrow> </mfrac> <mo>-</mo> <mfrac> <mrow> <mtext mathvariant=\"italic\">d</mtext> <mtext mathvariant=\"italic\">q</mtext> </mrow> <mrow> <mtext mathvariant=\"italic\">d</mtext> <mtext mathvariant=\"italic\">t</mtext> </mrow> </mfrac> <mtext mathvariant=\"italic\">R</mtext> <mo>-</mo> <mtext mathvariant=\"italic\">L</mtext> <mfrac> <mrow> <mtext mathvariant=\"italic\">d</mtext> <mtext mathvariant=\"italic\">i</mtext> </mrow> <mrow> <mtext mathvariant=\"italic\">d</mtext> <mtext mathvariant=\"italic\">t</mtext> </mrow> </mfrac> <mo>=</mo> <mn>0</mn> </mrow> </math><br /><br /><math> <mrow> <mo>\u21d2</mo> <mspace width=\"0.5em\"></mspace> <mtext mathvariant=\"italic\">d</mtext> <mtext mathvariant=\"italic\">q</mtext> <mo>=</mo> <mfrac> <mrow> <mtext mathvariant=\"italic\">d</mtext> <mi>\u03d5</mi> <mo>-</mo> <mtext mathvariant=\"italic\">L</mtext> <mtext mathvariant=\"italic\">d</mtext> <mtext mathvariant=\"italic\">i</mtext> </mrow> <mrow> <mtext mathvariant=\"italic\">R</mtext> </mrow> </mfrac> </mrow> </math><br /><br /><math> <mrow> <mspace width=\"0.5em\"></mspace> <mtext mathvariant=\"italic\">\u0394</mtext> <mtext mathvariant=\"italic\">q</mtext> <mo>=</mo> <mfrac> <mrow> <mtext mathvariant=\"italic\">\u0394</mtext> <mi>\u03d5</mi> <mo>-</mo> <mtext mathvariant=\"italic\">L</mtext> <mtext mathvariant=\"italic\">\u0394</mtext> <mtext mathvariant=\"italic\">I</mtext> </mrow> <mrow> <mtext mathvariant=\"italic\">R</mtext></mrow></mfrac></mrow></math><br /><br /><math> <mrow> <mspace width=\"0.5em\"></mspace> <mo>=</mo> <mfrac> <mrow> <mn>1</mn> </mrow> <mrow> <mtext mathvariant=\"italic\">R</mtext> </mrow> </mfrac> <mo>[</mo> <mfenced close=\")\" open=\"(\" separators=\",\"> <mrow> <msub> <mtext mathvariant=\"italic\">\u03d5</mtext> <mn>1</mn> </msub> <mo>-</mo> <msub> <mtext mathvariant=\"italic\">\u03d5</mtext> <mn>2</mn> </msub> </mrow> </mfenced> <mo>-</mo> <mtext mathvariant=\"italic\">L</mtext>&nbsp;<mrow><msub><mtext mathvariant=\"italic\">i</mtext> <mn>1</mn> </msub> </mrow> </mfenced> <mo>]</mo> </mrow> </math><br /><br /><math xmlns=\"http://www.w3.org/1998/Math/MathML\"><mspace width=\"0.5em\"></mspace><mtext mathvariant=\"italic\">\u0394</mtext><mtext mathvariant=\"italic\">q</mtext><mo>=</mo><mfrac><mn>1</mn><mtext mathvariant=\"italic\">R</mtext></mfrac><mo>[</mo><mfrac><mrow><msub><mtext mathvariant=\"italic\">\u03bc</mtext><mn>0</mn></msub><mi>\u2113</mi><msub><mtext mathvariant=\"italic\">I</mtext><mn>0</mn></msub></mrow><mrow><mn>2</mn><mtext mathvariant=\"italic\">\u03c0</mtext></mrow></mfrac><mi>ln</mi><mfenced><mn>2</mn></mfenced><mo>-</mo><mtext mathvariant=\"italic\">L</mtext><msub><mtext mathvariant=\"italic\">i</mtext><mn>1</mn></msub><mo>]</mo></math>", "image": null}, "videoSolution": null, "numericalLowerLimit": null, "numericalUpperLimit": null, "cpyqbSubjects": ["61bb58181213731910ea0b70", "61c055eae8ce0dc8a5c62d33", "616057750283de43c87e3e1b", "61964fe0a5a5260118868021", "61964f81a5a526011886801d", "629f39e4ac11b26562e0625b", "616057920283de43c87e3e1e", "615f0c729476412f48314dab", "61a8a2c2e8ce0dc8a5c62d2d", "629105adee9e3ae00d63352b", "629f385f263330a77be9fa7d", "616056cd0283de43c87e3e15", "616057190283de43c87e3e18", "62962075e7f8e9ac4daeafd7", "64d50bd73df7f4a7f3017f6f", "66b79b34d4b564dfab4f94cc", "678ea9a09cc79e5f592bdc11", "67fa5fef4468eb1307ceb0ad", "6807d2ad647479b8e8696479"], "cpyqbChapters": ["61602427cba2fa9ed9e72f82", "61bb82298adb7037e33f5e90", "6160242956b3f4e9b44d7836", "6160242ae6745f9dfbbf4eef", "61964c8f2c567a99ecc74113", "61602429b42b3007928c2021", "61e7bd7f4ea4ca4e8a493885", "6160242803cde39247fbcbae", "61964c8f782d0b7527c95ac9", "61c089b6c9a8a8e3433b1b2d", "6296212226b6eca689110f83", "629f390b0e3e15ddeed9a64e", "629109ebf9b127a2e6449c7b", "629f3a90c4d08c5950ee686b", "64eb06bf3118f713ecfef066", "66d58539a75f05ee8564f55f", "67921d671d5b5072da5e9ac6", "67fdff47378e1624ea7b6991", "6809202e3a10446a207fdf0c"], "cpyqbExams": ["615f0e999476412f48314daf", "616059af0283de43c87e3e23"]}}