{"success": true, "message": "Fetched question.", "data": {"showTimer": true, "showAttemptInsight": true, "playSounds": true, "dontShowCorrectAnswerImmediately": false, "_id": "648b5a69417cc3fb48d66fe5", "classes": [], "exams": ["615d76b2c52ffa3c944600df"], "subjects": ["615d708dbd4a37c4058ee5a8"], "chapters": ["615d6fed2b295b085ab6eb98"], "topics": [], "concepts": [], "previousYearPapers": [{"_id": "615d92edde3d91842a5cf812", "title": "JEE Main 2021 (18 Mar Shift 1)", "isVisible": true}], "type": "numerical", "level": 1, "approximateTimeRequired": 90, "question": {"text": "A particle performs simple harmonic motion with a period of <math xmlns=\"http://www.w3.org/1998/Math/MathML\"><mn>2</mn></math> second. The time taken by the particle to cover a displacement equal to half of its amplitude from the mean position is <math xmlns=\"http://www.w3.org/1998/Math/MathML\"><mfrac><mn>1</mn><mi>a</mi></mfrac><mo>&#160;</mo><mi mathvariant=\"normal\">s</mi><mo>.</mo></math> The value of <math xmlns=\"http://www.w3.org/1998/Math/MathML\"><mi>a</mi></math> to the nearest integer is", "image": null}, "options": [], "correctValue": "6", "solution": {"text": "<p><img src=\"https://cdn-question-pool.getmarks.app/pyq/jee_main/bd7112a6-300d-4f49-b624-06544c4ffb75-image.png\" style=\"width: 337px; height: 112px;\" /></p><p><math xmlns=\"http://www.w3.org/1998/Math/MathML\"><mi>t</mi><mo>=</mo><mfrac><mn>2</mn><mn>12</mn></mfrac><mo>=</mo><mfrac><mn>1</mn><mn>6</mn></mfrac></math><br /><math xmlns=\"http://www.w3.org/1998/Math/MathML\"><mo>&#8756;</mo></math> Correct answer <math xmlns=\"http://www.w3.org/1998/Math/MathML\"><mo>=</mo><mn>6</mn><mo>.</mo><mn>00</mn></math></p>", "image": null}, "videoSolution": null, "questionLabels": [], "numericalLowerLimit": 6, "numericalUpperLimit": 6, "masterId": "MOGJMPYQ86647702", "source": "EM", "bucket": "Must Do Ques (JEE Main) - Any Difficulty", "category": null, "microConcepts": [], "imageBaseUrl": null, "helperText": null, "isRemoved": false, "cpyqbSubjects": ["61bb58181213731910ea0b70", "61c055eae8ce0dc8a5c62d33", "616057750283de43c87e3e1b", "61964fe0a5a5260118868021", "61964f81a5a526011886801d", "629f39e4ac11b26562e0625b", "616057920283de43c87e3e1e", "615f0c729476412f48314dab", "61a8a2c2e8ce0dc8a5c62d2d", "629105adee9e3ae00d63352b", "629f385f263330a77be9fa7d", "616056cd0283de43c87e3e15", "616057190283de43c87e3e18", "62962075e7f8e9ac4daeafd7", "64d50bd73df7f4a7f3017f6f", "66b79b34d4b564dfab4f94cc", "678ea9a09cc79e5f592bdc11", "67fa5fef4468eb1307ceb0ad", "6807d2ad647479b8e8696479"], "cpyqbChapters": ["616023f6105ab3ae165341bb", "61964c8546e3d33b1892d09e", "61c089968734366dae3f36bc", "61bb8217aebeece6abdbe72b", "616023f783ceaeb51fe46126", "616023f4946fab7b921bf28d", "61964c86b98428bab9bd89d6", "616023f51f5c75c27ba35382", "616023f36324da677f8a7444", "61e7bd75347c64f272d9d8bb", "62962124ca45d71899e3dfe9", "629f390dd4f42c0deef34eab", "629109ef78779344f598426c", "629f3a921cf4dc490b09a322", "64eb06c13118f713ecfef085", "66d5853ca75f05ee8564f57b", "67921d681d5b5072da5e9acb", "67fdff4e378e1624ea7b69f4", "6809202b3a10446a207fdee4"], "cpyqbExams": ["615f0e999476412f48314daf", "616059af0283de43c87e3e23"]}}