{"success": true, "message": "Fetched question.", "data": {"showTimer": true, "showAttemptInsight": true, "playSounds": true, "dontShowCorrectAnswerImmediately": false, "_id": "648b5a68417cc3fb48d66bc4", "classes": [], "exams": ["615d76b2c52ffa3c944600df"], "subjects": ["615d708dbd4a37c4058ee5a8"], "chapters": ["615d6fec2b295b085ab6eb8d"], "topics": [], "concepts": [], "previousYearPapers": [{"_id": "615d92ecde3d91842a5cf806", "title": "JEE Main 2020 (06 Sep Shift 1)", "isVisible": true}], "type": "singleCorrect", "level": 2, "approximateTimeRequired": 150, "question": {"text": "<p>A clock has a continuously moving second&#39;s hand of&nbsp;<math xmlns=\"http://www.w3.org/1998/Math/MathML\"><mn>0</mn><mo>.</mo><mn>1</mn><mi mathvariant=\"normal\">m</mi></math> length. The average acceleration of the tip of the hand (in units of <math xmlns=\"http://www.w3.org/1998/Math/MathML\"><msup><mi>ms</mi><mrow><mo>-</mo><mn>2</mn></mrow></msup></math>&nbsp;]) is of the order of :</p>", "image": null}, "options": [{"id": "x0w4U", "text": "<math xmlns=\"http://www.w3.org/1998/Math/MathML\"><msup><mn>10</mn><mrow><mo>-</mo><mn>3</mn></mrow></msup></math>", "isCorrect": true, "image": null}, {"id": "AHN1p", "text": "<math xmlns=\"http://www.w3.org/1998/Math/MathML\"><msup><mn>10</mn><mrow><mo>-</mo><mn>4</mn></mrow></msup></math>", "isCorrect": false, "image": null}, {"id": "N1hpT", "text": "<math xmlns=\"http://www.w3.org/1998/Math/MathML\"><msup><mn>10</mn><mrow><mo>-</mo><mn>2</mn></mrow></msup></math>", "isCorrect": false, "image": null}, {"id": "VXdnA", "text": "<math xmlns=\"http://www.w3.org/1998/Math/MathML\"><msup><mn>10</mn><mrow><mo>-</mo><mn>1</mn></mrow></msup></math>", "isCorrect": false, "image": null}], "correctValue": null, "solution": {"text": "<p>The instantaneous acceleration of tip is given by</p><p><math xmlns=\"http://www.w3.org/1998/Math/MathML\"><mi>ac</mi><mo>=</mo><msup><mi>&#969;</mi><mn>2</mn></msup><mi mathvariant=\"normal\">R</mi><mo>=</mo><msup><mfenced><mfrac><mrow><mn>2</mn><mi>&#960;</mi></mrow><mn>60</mn></mfrac></mfenced><mn>2</mn></msup><mo>&#215;</mo><mn>0</mn><mo>.</mo><mn>1</mn><mo>=</mo><mfrac><mn>1</mn><mn>900</mn></mfrac><mo>&#8776;</mo><msup><mn>10</mn><mrow><mo>-</mo><mn>3</mn></mrow></msup></math></p><p>&nbsp;</p>", "image": null}, "videoSolution": null, "questionLabels": [], "masterId": "MOGJMPYQ50986164", "source": "EM", "bucket": "Must Do Ques (JEE Main) - Any Difficulty", "numericalLowerLimit": null, "numericalUpperLimit": null, "category": null, "microConcepts": [], "imageBaseUrl": null, "helperText": null, "isRemoved": false, "cpyqbSubjects": ["61bb58181213731910ea0b70", "61c055eae8ce0dc8a5c62d33", "616057750283de43c87e3e1b", "61964fe0a5a5260118868021", "61964f81a5a526011886801d", "629f39e4ac11b26562e0625b", "616057920283de43c87e3e1e", "615f0c729476412f48314dab", "61a8a2c2e8ce0dc8a5c62d2d", "629105adee9e3ae00d63352b", "629f385f263330a77be9fa7d", "616056cd0283de43c87e3e15", "616057190283de43c87e3e18", "62962075e7f8e9ac4daeafd7", "64d50bd73df7f4a7f3017f6f", "66b79b34d4b564dfab4f94cc", "678ea9a09cc79e5f592bdc11", "67fa5fef4468eb1307ceb0ad", "6807d2ad647479b8e8696479"], "cpyqbChapters": ["616023b19c52e0f28ddb0775", "616023b0de8166998bc42c6d", "616023af43c51275f749f558", "61964c73d9833a69946df6f2", "61e7bd6f3bf0edf6b5de3a0b", "61964c746f9d7c1ee88dadf2", "616023aeab028caf34f8696e", "61c089866e775b4063ccd8a4", "616023b0785fa46404399f50", "61bb820e7ded9395491665d7", "629109efb7e6d88372f6f913", "629f390d082fd4386414ddf1", "629f3a923db4e88dec15f6fb", "629621249a4459f8a4446124", "64eb06be3118f713ecfef063", "66d58535a75f05ee8564f537", "67921d621d5b5072da5e9a97", "67fdff56378e1624ea7b6a62", "6809202e3a10446a207fdf09"], "cpyqbExams": ["615f0e999476412f48314daf", "616059af0283de43c87e3e23"]}}