{"success": true, "message": "Fetched question.", "data": {"showTimer": true, "showAttemptInsight": true, "playSounds": true, "dontShowCorrectAnswerImmediately": false, "_id": "66bcbed9ae81d148616b1c9b", "type": "singleCorrect", "level": 1, "category": null, "approximateTimeRequired": 40, "imageBaseUrl": null, "helperText": null, "source": "MOG", "classes": [], "exams": ["615d76e4c52ffa3c944600e1"], "subjects": ["615d70f9a489afa3080ade2d"], "chapters": ["615d6ff22b295b085ab6ec14"], "topics": [], "concepts": [], "microConcepts": [], "questionLabels": [], "previousYearPapers": [{"_id": "64b850032a7d64ecd80b00af", "title": "NEET 2012 (Mains)", "isVisible": true}], "question": {"text": "The second stage of hydrosere is occupied by plants like", "image": null}, "options": [{"id": "EPf9j", "text": "Azolla", "image": null, "isCorrect": false}, {"id": "zXyjA", "text": "Typha", "image": null, "isCorrect": false}, {"id": "GAZvc", "text": "Salix", "image": null, "isCorrect": false}, {"id": "MUpMG", "text": "Vallisneria", "image": null, "isCorrect": true}], "correctValue": null, "solution": {"text": "Hydrosere originating in a pond starts with colonization of some phytoplanktons which forms the pioneer plant community. The stages are\nIst-Bacteria, Blue-green algae, Algae\nIInd-Hydrilla Potamogeton, Vallisneria\nIIIrd-Nelumbo, Nymphaea, Trapa, Azolla, Wolffia\nIVth-Typha, Sagitaria\nV-Juncus, Cyperus\nVI-Salix, Populus, Almus", "image": null}, "videoSolution": null, "masterId": "MOGNEPYQ71508503", "numericalLowerLimit": null, "numericalUpperLimit": null, "bucket": "", "isRemoved": false, "cpyqbSubjects": ["616057290283de43c87e3e1a", "616057b00283de43c87e3e20", "64d50cd33df7f4a7f3017f71", "66b79bbbd4b564dfab4f94d2", "67fa60d64468eb1307ceb0b0", "6807d392647479b8e869647c"], "cpyqbChapters": ["616025f47a4fd69d9d3cdeb4", "616025f57988d9bdbbe02f3e", "64eb06ff3118f713ecfef301", "66d58551a75f05ee8564f650", "67fdff49378e1624ea7b69ae", "68091fc63a10446a207fdacb"], "cpyqbExams": ["616059d70283de43c87e3e24", "616059730283de43c87e3e22"]}, "fetch_status": true}