{"success": true, "message": "Fetched question.", "data": {"hasAccess": false, "showTimer": true, "showAttemptInsight": true, "playSounds": true, "dontShowCorrectAnswerImmediately": false, "_id": "66bcbfaaae81d148616b2321", "type": "singleCorrect", "level": 3, "category": null, "approximateTimeRequired": 150, "imageBaseUrl": null, "helperText": null, "source": "1", "classes": [], "exams": ["615d76e4c52ffa3c944600e1"], "subjects": ["615d708dbd4a37c4058ee5a8"], "chapters": ["615d6fed2b295b085ab6eb9e"], "topics": [], "concepts": [], "microConcepts": [], "questionLabels": [], "previousYearPapers": [{"_id": "615d92f0de3d91842a5cf856", "title": "NEET 2018", "isVisible": true}], "question": {"text": "A metallic rod of mass per unit length <math><mn>0.5</mn><mi>&#160;</mi><mi>kg</mi><mi>&#160;</mi><msup><mrow><mn>m</mn></mrow><mrow><mo>-</mo><mn>1</mn></mrow></msup></math> is lying horizontally on a smooth inclined plane which makes an angle <math><msup><mrow><mn>30</mn></mrow><mrow><mi>o</mi></mrow></msup></math> with the horizontal. The rod is not allowed to slide down by flowing a current through it when a magnetic field of induction <math xmlns=\"http://www.w3.org/1998/Math/MathML\"><mn>0</mn><mo>.</mo><mn>25</mn><mo>&#160;</mo><mi mathvariant=\"normal\">T</mi></math> is acting on it in the vertical direction. The current flowing in the rod to keep it stationary is", "image": null}, "options": [{"id": "0FNeI", "text": "<math xmlns=\"http://www.w3.org/1998/Math/MathML\"><mn>14</mn><mo>.</mo><mn>76</mn><mo>&#160;</mo><mi mathvariant=\"normal\">A</mi></math>", "image": null, "isCorrect": false}, {"id": "LslZq", "text": "<math xmlns=\"http://www.w3.org/1998/Math/MathML\"><mn>5</mn><mo>.</mo><mn>98</mn><mo>&#160;</mo><mi mathvariant=\"normal\">A</mi></math>", "image": null, "isCorrect": false}, {"id": "UnGPu", "text": "<math xmlns=\"http://www.w3.org/1998/Math/MathML\"><mn>7</mn><mo>.</mo><mn>14</mn><mo>&#160;</mo><mi mathvariant=\"normal\">A</mi></math>", "image": null, "isCorrect": false}, {"id": "TANxI", "text": "<math xmlns=\"http://www.w3.org/1998/Math/MathML\"><mn>11</mn><mo>.</mo><mn>32</mn><mo>&#160;</mo><mi mathvariant=\"normal\">A</mi></math>", "image": null, "isCorrect": true}], "correctValue": null, "solution": {"text": "<p>For equilibrium of conductor<br /><br /><img src=\"https://cdn-question-pool.getmarks.app/pyq/neet/c7357b59-4973-46e5-94cb-1c515f465a85-image.png\" style=\"width: 280px; height: 253px;\" /><br /><math><mi>i</mi><mi>l</mi><mi>B</mi><mrow><mrow><mi mathvariant=\"normal\">cos</mi></mrow><mo>&#8289;</mo><mrow><mi>&#952;</mi></mrow></mrow><mo>=</mo><mi>m</mi><mi>g</mi><mrow><mrow><mi mathvariant=\"normal\">sin</mi></mrow><mo>&#8289;</mo><mrow><mi>&#952;</mi></mrow></mrow></math><br /><br /><math><mi>i</mi><mo>=</mo><mfrac><mrow><mi>m</mi><mi>g</mi></mrow><mrow><mi>l</mi><mi>B</mi></mrow></mfrac><mrow><mrow><mi mathvariant=\"normal\">tan</mi></mrow><mo>&#8289;</mo><mrow><mi>&#952;</mi></mrow></mrow><mo>=</mo><mfenced separators=\"|\"><mrow><mfrac><mrow><mi>m</mi></mrow><mrow><mi>l</mi></mrow></mfrac></mrow></mfenced><mfrac><mrow><mi>g</mi><mrow><mrow><mi mathvariant=\"normal\">tan</mi></mrow><mo>&#8289;</mo><mrow><mi>&#952;</mi></mrow></mrow></mrow><mrow><mi>B</mi></mrow></mfrac><mi>&#160;</mi></math><br /><br /><math><mi>i</mi><mo>=</mo><mn>0.5</mn><mo>&#215;</mo><mfrac><mrow><mn>9.8</mn></mrow><mrow><mn>0.25</mn></mrow></mfrac><mo>&#215;</mo><mfrac><mrow><mn>1</mn></mrow><mrow><msqrt><mn>3</mn></msqrt></mrow></mfrac><mo>=</mo><mn>11.3</mn><mi>&#160;A</mi><mo>.</mo></math></p>", "image": null}, "videoSolution": {"videoId": "ede28cc071964398a06338cde3f5ae3f", "provider": "vdocipher", "thumbnailLight": "https://d1z78r8i505acl.cloudfront.net/poster/4WaMZuRgAAIak.480.jpeg", "thumbnailDark": "https://d1z78r8i505acl.cloudfront.net/poster/4WaMZuRgAAIak.480.jpeg", "premiumModules": [{"premiumModuleId": "6628114842d540dfcb148ecb", "isFree": false}, {"premiumModuleId": "6788cc0b2dbc1ecacabb7026", "isFree": false}], "description": "NEET"}, "masterId": "MOGNEPYQ62094924", "numericalLowerLimit": null, "numericalUpperLimit": null, "bucket": "", "isRemoved": false, "cpyqbSubjects": ["61bb58181213731910ea0b70", "61c055eae8ce0dc8a5c62d33", "616057750283de43c87e3e1b", "61964fe0a5a5260118868021", "61964f81a5a526011886801d", "629f39e4ac11b26562e0625b", "616057920283de43c87e3e1e", "615f0c729476412f48314dab", "61a8a2c2e8ce0dc8a5c62d2d", "629105adee9e3ae00d63352b", "629f385f263330a77be9fa7d", "616056cd0283de43c87e3e15", "616057190283de43c87e3e18", "62962075e7f8e9ac4daeafd7", "64d50bd73df7f4a7f3017f6f", "66b79b34d4b564dfab4f94cc", "678ea9a09cc79e5f592bdc11", "67fa5fef4468eb1307ceb0ad", "6807d2ad647479b8e8696479"], "cpyqbChapters": ["61602420ae6dd863a9d1d7d8", "6160241f1a832a8dea12fbf0", "616024236098c3dc0cc3e764", "61602422b42cfaef18219875", "616024227e2ba4496fdd4552", "61964c8c8d7ade9f02022966", "61c08987636555dc34527e11", "61e7bd70643383b6c26bfb1d", "61964c8e8811f774a40dd9f1", "62962123b040395dcc21a751", "629f3a9143c2c00ea1d2f857", "629109edc3391b7808eb05af", "61bb820fdb486fa25580e4bd", "629f390c27047111eccefe03", "64eb06c03118f713ecfef077", "66d5853aa75f05ee8564f568", "67921d601d5b5072da5e9a88", "67fdff4f378e1624ea7b6a03", "6809202a3a10446a207fded7"], "cpyqbExams": ["616059d70283de43c87e3e24", "616059730283de43c87e3e22"], "needToPurchaseModules": ["6628114842d540dfcb148ecb", "6788cc0b2dbc1ecacabb7026"], "isLocked": true}}