{"success": true, "message": "Fetched question.", "data": {"showTimer": true, "showAttemptInsight": true, "playSounds": true, "dontShowCorrectAnswerImmediately": false, "_id": "64b169fdf23ac7d519f9b053", "type": "numerical", "level": 2, "category": null, "approximateTimeRequired": 150, "imageBaseUrl": null, "helperText": null, "source": "MOG", "classes": [], "exams": ["615d76cfc52ffa3c944600e0"], "subjects": ["615d708dbd4a37c4058ee5a8"], "chapters": ["615d6fed2b295b085ab6eb95"], "topics": [], "concepts": [], "microConcepts": [], "questionLabels": [], "previousYearPapers": [{"_id": "620a8a1f77301f65c2f92c46", "title": "JEE Advanced 2010 (Paper 1)", "isVisible": true}], "question": {"text": "A piece of ice (heat capacity $=2100 \\mathrm{~J} \\mathrm{~kg}^{-1}{ }^{\\circ} \\mathrm{C}^{-1}$ and latent heat $=3.36 \\times 10^5 \\mathrm{~J} \\mathrm{~kg}^{-1}$ ) of mass $\\mathrm{m}$ gram is at $-5^{\\circ} \\mathrm{C}$ at atmospheric pressure. It is given $420 \\mathrm{~J}$ of heat so that the ice starts melting. Finally when the ice-water mixture is in equilibrium, it is found that $1 \\mathrm{~g}$ of ice has melted. Assuming there is no other heat exchange in the process, the value of $m$ is", "image": null}, "options": [], "correctValue": "8", "solution": {"text": "Language of question is slightly wrong. As heat capacity and specific heat are two different physical quantities. Unit $\\mathrm{J}-\\mathrm{kg}^{-1} \\cdot{ }^{\\circ} \\mathrm{C}^{-1}$. The heat capacity given in the question is really the specific heat. Now applying the heat exchange equation.\n$$\n\\begin{array}{r}\n420=\\left(m \\times 10^{-3}\\right)(2100)(5)+\\left(1 \\times 10^{-3}\\right) \\\\\n\\left(3.36 \\times 10^5\\right)\n\\end{array}\n$$\nSolving this equation we get,\n$$\nm=8 \\mathrm{~g}\n$$\n$\\therefore$ The correct answer is 8 .", "image": null}, "videoSolution": null, "masterId": "MOGJAPYQ04311012", "numericalLowerLimit": 8, "numericalUpperLimit": 8, "bucket": "", "isRemoved": false, "cpyqbSubjects": ["61bb58181213731910ea0b70", "61c055eae8ce0dc8a5c62d33", "616057750283de43c87e3e1b", "61964fe0a5a5260118868021", "61964f81a5a526011886801d", "629f39e4ac11b26562e0625b", "616057920283de43c87e3e1e", "615f0c729476412f48314dab", "61a8a2c2e8ce0dc8a5c62d2d", "629105adee9e3ae00d63352b", "629f385f263330a77be9fa7d", "616056cd0283de43c87e3e15", "616057190283de43c87e3e18", "62962075e7f8e9ac4daeafd7", "64d50bd73df7f4a7f3017f6f", "66b79b34d4b564dfab4f94cc", "678ea9a09cc79e5f592bdc11", "67fa5fef4468eb1307ceb0ad", "6807d2ad647479b8e8696479"], "cpyqbChapters": ["616023e599225f756e5df101", "616023e3445073e7f19122db", "61bb8229fce3576e46202d7d", "616023e0ffc8649daddda513", "61e7bd7f80092b5aa328b5a1", "616023e23a74832357599443", "616023e361589c931bc035b7", "61964c81150b027922bafad8", "61c089b4384657354ede4c09", "61964c81e74f86f9041974e2", "629f390e0537a44301966fe8", "629621250160e8ee846a120c", "629109f1da1b4d5a11b7952f", "629f3a930c61425b93824746", "64eb06bf3118f713ecfef06f", "66d58553a75f05ee8564f668", "67921d611d5b5072da5e9a8e", "67fdff4f378e1624ea7b69fd", "680920293a10446a207fdec5"], "cpyqbExams": ["616059150283de43c87e3e21"]}, "fetch_status": true}