{"success": true, "message": "Fetched question.", "data": {"showTimer": true, "showAttemptInsight": true, "playSounds": true, "dontShowCorrectAnswerImmediately": false, "_id": "615454d72882d47c555be5cd", "type": "singleCorrect", "level": null, "category": null, "approximateTimeRequired": null, "imageBaseUrl": null, "helperText": null, "source": "NTAS1", "classes": [], "exams": ["615d76e4c52ffa3c944600e1"], "subjects": ["615d70f9a489afa3080ade2d"], "chapters": ["615d6ff02b295b085ab6ebf6"], "topics": [], "concepts": [], "microConcepts": [], "questionLabels": [{"title": "NTA Abhyas Paper", "value": "43", "isVisible": true}], "previousYearPapers": [], "question": {"text": "Which of the following two features are present in meiosis but absent in mitosis?", "image": null}, "options": [{"id": "bPJoK", "text": "Pairing of non-homologous chromosome", "image": null, "isCorrect": false}, {"id": "TAmGS", "text": "Pairing of homologous chromosome and recombination between them", "image": null, "isCorrect": true}, {"id": "m2aIG", "text": "Replication of chromosome", "image": null, "isCorrect": false}, {"id": "hUaUL", "text": "All of these", "image": null, "isCorrect": false}], "correctValue": null, "solution": {"text": "Pairing of homologous chromosomes and recombination or crossing over between genes occurs only in meiosis and is absent in mitosis.", "image": null}, "videoSolution": null, "numericalLowerLimit": null, "numericalUpperLimit": null, "cpyqbSubjects": ["616057290283de43c87e3e1a", "616057b00283de43c87e3e20", "64d50cd33df7f4a7f3017f71", "66b79bbbd4b564dfab4f94d2", "67fa60d64468eb1307ceb0b0", "6807d392647479b8e869647c"], "cpyqbChapters": ["6160258f8fcd4a56da235ad1", "6160258e3b31e13c06dc70b4", "64eb06d23118f713ecfef130", "66d58564a75f05ee8564f704", "67fdff3b378e1624ea7b6913", "68091fbc3a10446a207fda5f"], "cpyqbExams": ["616059d70283de43c87e3e24", "616059730283de43c87e3e22"]}, "fetch_status": true}