{"success": true, "message": "Fetched question.", "data": {"showTimer": true, "showAttemptInsight": true, "playSounds": true, "dontShowCorrectAnswerImmediately": false, "_id": "6151e8631978c9460081128c", "type": "singleCorrect", "level": null, "category": null, "approximateTimeRequired": null, "imageBaseUrl": null, "helperText": null, "source": "NTAS1", "classes": [], "exams": ["615d76b2c52ffa3c944600df"], "subjects": ["615d708dbd4a37c4058ee5a8"], "chapters": ["615d6fec2b295b085ab6eb8e"], "topics": [], "concepts": [], "microConcepts": [], "questionLabels": [{"title": "NTA Abhyas Paper", "value": "84", "isVisible": true}], "previousYearPapers": [], "question": {"text": "A hanging block of mass <math xmlns=\"http://www.w3.org/1998/Math/MathML\"><msup><mi mathvariant=\"normal\">m</mi><mo>'</mo></msup></math>&nbsp;prevents the smaller block of mass&nbsp;<math><mtext>m</mtext> </math> from slipping over a movable triangular block of mass <math> <mtext>M</mtext></math>. All the surfaces are frictionless and the strings and the pulleys are light. Value of mass&nbsp;<math xmlns=\"http://www.w3.org/1998/Math/MathML\"><msup><mi mathvariant=\"normal\">m</mi><mo>'</mo></msup></math>&nbsp;in terms of&nbsp;<math xmlns=\"http://www.w3.org/1998/Math/MathML\"><mi mathvariant=\"normal\">m</mi></math>,&nbsp;<math xmlns=\"http://www.w3.org/1998/Math/MathML\"><mi mathvariant=\"normal\">M</mi></math>&nbsp;and&nbsp;<math xmlns=\"http://www.w3.org/1998/Math/MathML\"><mi mathvariant=\"normal\">\u03b8</mi></math>&nbsp;is<br />\r<br />\r<img alt=\"\" src=\"https://cdn-question-pool.getmarks.app/nta_abhyas/jee_main/images/dsvavds.jpg\" style=\"max-width:100%; object-fit:contain\" style=\"width: 200px; height: 136px;\" />", "image": null}, "options": [{"id": "mFa6E", "text": "<math> <mrow> <mfenced close=\"]\" open=\"[\" separators=\",\"> <mrow> <mfrac> <mrow> <mtext>m</mtext> <mo>+</mo> <mtext>M</mtext> </mrow> <mrow> <mtext>cot</mtext> <mtext>\u03b8</mtext> <mo>-</mo> <mn>1</mn> </mrow> </mfrac> </mrow> </mfenced> </mrow> </math>", "image": null, "isCorrect": true}, {"id": "jWbMr", "text": "<math><mrow>  <mfenced open=\"[\" close=\"]\" separators=\",\">    <mrow>      <mfrac>        <mrow>          <mtext>m</mtext>          <mo>-</mo>          <mtext>M</mtext>        </mrow>        <mrow>          <mtext>cot</mtext>          <mtext>&theta;</mtext>          <mo>+</mo>          <mn>1</mn>        </mrow>      </mfrac>    </mrow>  </mfenced></mrow></math>", "image": null, "isCorrect": false}, {"id": "gOqzZ", "text": "<math><mrow>  <mfenced open=\"[\" close=\"]\" separators=\",\">    <mrow>      <mfrac>        <mrow>          <mtext>m</mtext>          <mo>-</mo>          <mtext>M</mtext>        </mrow>        <mrow>          <mtext>cot</mtext>          <mtext>&theta;</mtext>          <mo>-</mo>          <mn>2</mn>        </mrow>      </mfrac>    </mrow>  </mfenced></mrow></math>", "image": null, "isCorrect": false}, {"id": "BtAFF", "text": "<math><mrow>  <mfenced open=\"[\" close=\"]\" separators=\",\">    <mrow>      <mfrac>        <mrow>          <mtext>m</mtext>          <mo>+</mo>          <mtext>M</mtext>        </mrow>        <mrow>          <mtext>cot</mtext>          <mtext>&theta;</mtext>          <mo>+</mo>          <mn>2</mn>        </mrow>      </mfrac>    </mrow>  </mfenced></mrow></math>", "image": null, "isCorrect": false}], "correctValue": null, "solution": {"text": "Pulling force is <math xmlns=\"http://www.w3.org/1998/Math/MathML\"><msup><mi mathvariant=\"normal\">m</mi><mo>'</mo></msup><mi mathvariant=\"normal\">g</mi></math>, while mass in motion is <math xmlns=\"http://www.w3.org/1998/Math/MathML\"><mi mathvariant=\"normal\">m</mi><mo>+</mo><mi mathvariant=\"normal\">M</mi><mo>+</mo><msup><mi mathvariant=\"normal\">m</mi><mo>'</mo></msup></math>. So acceleration of the system will be given by<br />\u200b<math xmlns=\"http://www.w3.org/1998/Math/MathML\"><mspace width=\"0.5em\"/><mspace width=\"0.5em\"/><mspace width=\"0.5em\"/><mspace width=\"0.5em\"/><mspace width=\"0.5em\"/><mspace width=\"0.5em\"/><mtext>a</mtext><mo>=</mo><mfrac><mrow><msup><mtext>m</mtext><mo>'</mo></msup><mtext>g</mtext></mrow><mfenced><mrow><mtext>m</mtext><mo>+</mo><mtext>M</mtext><mo>+</mo><msup><mtext>m</mtext><mo>'</mo></msup></mrow></mfenced></mfrac><mspace width=\"0.5em\"/><mspace width=\"0.5em\"/><mspace width=\"0.5em\"/><mspace width=\"0.5em\"/><mspace width=\"0.5em\"/><mspace width=\"0.5em\"/><mspace width=\"0.5em\"/><mtext>....(i)</mtext></math><br /><br />Mass&nbsp;<math xmlns=\"http://www.w3.org/1998/Math/MathML\"><mi mathvariant=\"normal\">m</mi></math> will not slide over <math xmlns=\"http://www.w3.org/1998/Math/MathML\"><mi mathvariant=\"normal\">M</mi></math> if&nbsp;<br /><br />&nbsp; &nbsp; &nbsp; &nbsp; &nbsp; a cos&theta; = g sin&theta;&nbsp;&nbsp;&nbsp;&nbsp;&nbsp;&nbsp;&nbsp;&nbsp;&nbsp;&nbsp;&nbsp;&nbsp;&nbsp;&nbsp;&nbsp;&nbsp;&nbsp; ....(ii)<br /><br />&nbsp;From equation (i) in (ii), we get<br /><br /><math> <mrow> <mspace width=\"0.5em\"></mspace> <mspace width=\"0.5em\"></mspace> <mfrac> <mrow> <msup> <mtext>m</mtext> <mo>&#8242;</mo> </msup> <mtext>g cos &#952;</mtext> </mrow> <mrow> <mfenced close=\")\" open=\"(\" separators=\",\"> <mrow> <mtext>m</mtext> <mo>+</mo> <mtext>M</mtext> <mo>+</mo> <msup> <mtext>m</mtext> <mo>&#8242;</mo> </msup> </mrow> </mfenced> </mrow> </mfrac> <mo>=</mo> <mtext>g sin</mtext> <mtext>&#952;</mtext> <mspace width=\"0.5em\"></mspace> <mspace width=\"0.5em\"></mspace> <mtext>or</mtext> <mspace width=\"0.5em\"></mspace> <mspace width=\"0.5em\"></mspace> <msup> <mtext>m</mtext> <mo>&#8242;</mo> </msup> <mo>=</mo> <mfenced close=\"]\" open=\"[\" separators=\",\"> <mrow> <mfrac> <mrow> <mtext>m</mtext> <mo>+</mo> <mtext>M</mtext> </mrow> <mrow> <mtext>cot &#952;</mtext> <mo>-</mo> <mn>1</mn> </mrow> </mfrac> </mrow> </mfenced> </mrow> </math>", "image": null}, "videoSolution": null, "numericalLowerLimit": null, "numericalUpperLimit": null, "cpyqbSubjects": ["61bb58181213731910ea0b70", "61c055eae8ce0dc8a5c62d33", "616057750283de43c87e3e1b", "61964fe0a5a5260118868021", "61964f81a5a526011886801d", "629f39e4ac11b26562e0625b", "616057920283de43c87e3e1e", "615f0c729476412f48314dab", "61a8a2c2e8ce0dc8a5c62d2d", "629105adee9e3ae00d63352b", "629f385f263330a77be9fa7d", "616056cd0283de43c87e3e15", "616057190283de43c87e3e18", "62962075e7f8e9ac4daeafd7", "64d50bd73df7f4a7f3017f6f", "66b79b34d4b564dfab4f94cc", "678ea9a09cc79e5f592bdc11", "67fa5fef4468eb1307ceb0ad", "6807d2ad647479b8e8696479"], "cpyqbChapters": ["616023b74026d68c120f2ba9", "616023b9c2e3bbfc3f2ecdd2", "616023b78dba43da23bef37e", "616023b542cfec4323be20b3", "61964c74ec1ca6c1a7365dcf", "61bb821fa52006d37a60e707", "61c089a30f62a0d239520145", "61964c76bae973f89e899882", "61e7bd7991a3d691658409aa", "616023b36f5a53c6a5d4ce42", "629f3a90cf4faea06a760897", "629109ec048d30f09d45ec7c", "629621223df2fbbc95bf297f", "629f390ce1a391b9376aa0de", "64eb06e13118f713ecfef1d7", "66d58567a75f05ee8564f723", "67921d641d5b5072da5e9aaa", "67fdff50378e1624ea7b6a0d", "680920323a10446a207fdf3e"], "cpyqbExams": ["615f0e999476412f48314daf", "616059af0283de43c87e3e23"]}}