{"success": true, "message": "Fetched question.", "data": {"showTimer": true, "showAttemptInsight": true, "playSounds": true, "dontShowCorrectAnswerImmediately": false, "_id": "615454d7b765c08796c771dc", "type": "singleCorrect", "level": null, "category": null, "approximateTimeRequired": null, "imageBaseUrl": null, "helperText": null, "source": "NTAS1", "classes": [], "exams": ["615d76e4c52ffa3c944600e1"], "subjects": ["615d70f9a489afa3080ade2d"], "chapters": ["615d6ff02b295b085ab6ebf8"], "topics": [], "concepts": [], "microConcepts": [], "questionLabels": [{"title": "NTA Abhyas Paper", "value": "36", "isVisible": true}], "previousYearPapers": [], "question": {"text": "Which of the following is incorrect about a bacterial cell?", "image": null}, "options": [{"id": "K6rt2", "text": "The 70S ribosome is mainly associated with plasma membrane and many a times shows polysome assembly.", "image": null, "isCorrect": false}, {"id": "nMl0N", "text": "The filament is the longest portion of the flagella and extends from the cell surface to the outside.", "image": null, "isCorrect": false}, {"id": "voe14", "text": "The plasma membrane extensions containing chromatophores basically helps in cellular respiration.", "image": null, "isCorrect": true}, {"id": "0aYi5", "text": "Gram staining is basically based on the thickness of peptidoglycan layer.", "image": null, "isCorrect": false}], "correctValue": null, "solution": {"text": "In some prokaryotes like cyanobacteria, there are other membranous extensions into the cytoplasm called chromatophores which contain pigments. These pigments facilitate photosynthesis.", "image": null}, "videoSolution": null, "numericalLowerLimit": null, "numericalUpperLimit": null, "cpyqbSubjects": ["616057290283de43c87e3e1a", "616057b00283de43c87e3e20", "64d50cd33df7f4a7f3017f71", "66b79bbbd4b564dfab4f94d2", "67fa60d64468eb1307ceb0b0", "6807d392647479b8e869647c"], "cpyqbChapters": ["6160259730adaa82c6000128", "616025966a1cef9af5528821", "64eb06d33118f713ecfef143", "66d58547a75f05ee8564f5ec", "67fdff3b378e1624ea7b6910", "68091fbf3a10446a207fda7a"], "cpyqbExams": ["616059d70283de43c87e3e24", "616059730283de43c87e3e22"]}, "fetch_status": true}